cache4py/__init__.py
cache4py/decorators.py
cache4py/exceptions.py
cache4py/utils.py
cache4py/storage/__init__.py
cache4py/storage/base.py
cache4py/storage/memcached.py
cache4py/storage/redis.py
tests/__init__.py
tests/test_basic.py
cache4py-0.0.1.dist-info/LICENSE
cache4py-0.0.1.dist-info/METADATA
cache4py-0.0.1.dist-info/WHEEL
cache4py-0.0.1.dist-info/top_level.txt
cache4py-0.0.1.dist-info/RECORD
