Metadata-Version: 2.1
Name: cache4py
Version: 0.0.1
Summary: Caching simplified.
Home-page: https://github.com/nitinl/cache4py
Author: Nitin Labhishetty
Author-email: nitinlabhishetty@gmail.com
License: MIT
Platform: UNKNOWN
Classifier: License :: OSI Approved :: MIT License
Classifier: Programming Language :: Python
Classifier: Programming Language :: Python :: 3
Classifier: Programming Language :: Python :: 3.6
Classifier: Programming Language :: Python :: Implementation :: CPython
Classifier: Programming Language :: Python :: Implementation :: PyPy
Requires-Python: >=3.6.0
Requires-Dist: redis
Requires-Dist: pymemcache
Provides-Extra: test
Requires-Dist: pytest; extra == 'test'
Requires-Dist: pytest-cov; extra == 'test'
